sps_parser/__init__.py
sps_parser/converters.py
sps_parser/models.py
sps_parser/utils.py
sps_parser-0.3.0.dist-info/LICENSE
sps_parser-0.3.0.dist-info/METADATA
sps_parser-0.3.0.dist-info/WHEEL
sps_parser-0.3.0.dist-info/top_level.txt
sps_parser-0.3.0.dist-info/RECORD
